Compiled from "z14.java"
public class z14 {
  public z14();
    Code:
       0: aload_0
       1: invokespecial #1                  // Method java/lang/Object."<init>":()V
       4: return

  public static void main(java.lang.String[]);
    Code:
       0: iconst_3
       1: newarray       int
       3: dup
       4: iconst_0
       5: iconst_1
       6: iastore
       7: dup
       8: iconst_1
       9: iconst_2
      10: iastore
      11: dup
      12: iconst_2
      13: iconst_3
      14: iastore
      15: astore_1
      16: aload_1
      17: invokestatic  #5                  // Method printArray:([I)V
      20: return
}