Compiled from "z9.java"
public class z9 extends Calculation {
  public z9();
    Code:
       0: aload_0
       1: invokespecial #1                  // Method Calculation."<init>":()V
       4: return

  public void multiplication(int, int);
    Code:
       0: aload_0
       1: iload_1
       2: iload_2
       3: imul
       4: putfield      #2                  // Field z:I
       7: getstatic     #3                  // Field java/lang/System.out:Ljava/io/PrintStream;
      10: aload_0
      11: getfield      #2                  // Field z:I
      14: invokedynamic #4,  0              // InvokeDynamic #0:makeConcatWithConstants:(I)Ljava/lang/String;
      19: invokevirtual #5                  // Method java/io/PrintStream.println:(Ljava/lang/String;)V
      22: return

  public static void main(java.lang.String[]);
    Code:
       0: bipush        20
       2: istore_1
       3: bipush        10
       5: istore_2
       6: new           #6                  // class z9
       9: dup
      10: invokespecial #7                  // Method "<init>":()V
      13: astore_3
      14: aload_3
      15: iload_1
      16: iload_2
      17: invokevirtual #8                  // Method addition:(II)V
      20: aload_3
      21: iload_1
      22: iload_2
      23: invokevirtual #9                  // Method Subtraction:(II)V
      26: aload_3
      27: iload_1
      28: iload_2
      29: invokevirtual #10                 // Method multiplication:(II)V
      32: return

  public void Subtraction(int, int);
    Code:
       0: aload_0
       1: iload_1
       2: iload_2
       3: invokespecial #11                 // Method Calculation.Subtraction:(II)V
       6: return

  public void addition(int, int);
    Code:
       0: aload_0
       1: iload_1
       2: iload_2
       3: invokespecial #12                 // Method Calculation.addition:(II)V
       6: return
}
